slackline/__init__.py
slackline/__main__.py
slackline/cli.py
slackline/commands/__init__.py
slackline/commands/base.py
slackline/commands/hello.py
slackline/commands/message.py
slackline-0.1.0.dist-info/DESCRIPTION.rst
slackline-0.1.0.dist-info/METADATA
slackline-0.1.0.dist-info/RECORD
slackline-0.1.0.dist-info/WHEEL
slackline-0.1.0.dist-info/entry_points.txt
slackline-0.1.0.dist-info/metadata.json
slackline-0.1.0.dist-info/top_level.txt
