Metadata-Version: 2.0
Name: slackline
Version: 0.1.0
Summary: A skeleton command line program in Python.
Home-page: https://github.com/samdfonseca/slackline
Author: Sam Fonseca
Author-email: samfonseca@utexas.edu
License: MIT
Keywords: cli
Platform: UNKNOWN
Classifier: Intended Audience :: Developers
Classifier: Topic :: Utilities
Classifier: License :: Public Domain
Classifier: Natural Language :: English
Classifier: Operating System :: OS Independent
Classifier: Programming Language :: Python :: 3
Classifier: Programming Language :: Python :: 3.6
Requires-Dist: docopt
Requires-Dist: slacker
Provides-Extra: test
Requires-Dist: coverage; extra == 'test'
Requires-Dist: pytest; extra == 'test'
Requires-Dist: pytest-cov; extra == 'test'
